ohms_law_pk/__init__.py
ohms_law_pk/ohms_law.py
ohms_law_pk-0.1.dist-info/LICENSE
ohms_law_pk-0.1.dist-info/METADATA
ohms_law_pk-0.1.dist-info/WHEEL
ohms_law_pk-0.1.dist-info/top_level.txt
ohms_law_pk-0.1.dist-info/RECORD
