Metadata-Version: 2.1
Name: ohms_law_pk
Version: 0.1
Summary: ohms Law calulator
Home-page: https://github.com/PavanKannan/ohms_law_pk
Author: Pavan Kannan
Author-email: pkannan@students.kennesaw.edu
Classifier: Programming Language :: Python :: 3
Classifier: License :: OSI Approved :: MIT License
Classifier: Operating System :: OS Independent
Requires-Python: >=3.2
License-File: LICENSE
